inspect_extensions.py
inspect_extensions-0.1.6.dist-info/METADATA
inspect_extensions-0.1.6.dist-info/WHEEL
inspect_extensions-0.1.6.dist-info/entry_points.txt
inspect_extensions-0.1.6.dist-info/top_level.txt
inspect_extensions-0.1.6.dist-info/RECORD
