Metadata-Version: 2.1
Name: inspect-extensions
Version: 0.1.6
Summary: Extensions for Python inspect module.
Home-page: https://github.com/dpizetta/inspect-extensions
Author: Daniel Cosmo Pizetta
Author-email: daniel.pizetta@usp.br
Maintainer: Daniel Cosmo Pizetta
Maintainer-email: daniel.pizetta@usp.br
License: MIT
Project-URL: Issues, https://github.com/dpizetta/inspect-extensions/issues
Project-URL: Docs, https://inspect-extensions.readthedocs.io/en/stable/index.html
Classifier: Development Status :: 4 - Beta
Classifier: Environment :: Console
Classifier: Intended Audience :: Customer Service
Classifier: Intended Audience :: End Users/Desktop
Classifier: Intended Audience :: Developers
Classifier: License :: OSI Approved :: MIT License
Classifier: Natural Language :: English
Classifier: Operating System :: MacOS
Classifier: Operating System :: Microsoft :: Windows
Classifier: Operating System :: POSIX
Classifier: Programming Language :: Python :: 3.6
Classifier: Programming Language :: Python :: 3.7
Classifier: Programming Language :: Python :: 3.8
Classifier: Programming Language :: Python :: 3.9
Classifier: Programming Language :: Python :: 3.10
Classifier: Programming Language :: Python :: 3.11
Classifier: Topic :: Documentation
Classifier: Topic :: Software Development :: Bug Tracking
Classifier: Topic :: Software Development :: Documentation
Classifier: Topic :: Software Development :: Debuggers
Classifier: Topic :: Software Development :: Libraries
Classifier: Topic :: Software Development :: Testing
Classifier: Topic :: Terminals
Requires-Dist: termcolor
